{
  "animateLoading": true,
  "borderRadius": "{{appsmith.theme.borderRadius.appBorderRadius}}",
  "bottomRow": 64,
  "dynamicBindingPathList": [
    {
      "key": "truncateButtonColor"
    },
    {
      "key": "fontFamily"
    },
    {
      "key": "borderRadius"
    }
  ],
  "dynamicHeight": "AUTO_HEIGHT",
  "dynamicTriggerPathList": [],
  "fontFamily": "{{appsmith.theme.fontFamily.appFont}}",
  "fontSize": "1.25rem",
  "fontStyle": "BOLD",
  "isLoading": false,
  "isVisible": true,
  "key": "fylcgxr3ev",
  "leftColumn": 0,
  "maxDynamicHeight": 9000,
  "minDynamicHeight": 4,
  "minWidth": 450,
  "mobileBottomRow": 4,
  "mobileLeftColumn": 0,
  "mobileRightColumn": 2,
  "mobileTopRow": 0,
  "needsErrorInfo": false,
  "originalBottomRow": 64,
  "originalTopRow": 60,
  "overflow": "NONE",
  "parentColumnSpace": 28.27347183227539,
  "parentId": "rrunai6ijy",
  "parentRowSpace": 10,
  "renderMode": "CANVAS",
  "responsiveBehavior": "fill",
  "rightColumn": 19,
  "shouldTruncate": false,
  "text": "课程属性\n",
  "textAlign": "LEFT",
  "textColor": "#231F20",
  "topRow": 60,
  "truncateButtonColor": "{{appsmith.theme.colors.primaryColor}}",
  "type": "TEXT_WIDGET",
  "version": 1,
  "widgetId": "p9z16pyfk5",
  "widgetName": "Text12"
}